{
  "format-version" : 2,
  "table-uuid" : "1fa6c6c7-d643-4bed-928c-9eea3062beaa",
  "location" : "/home/jovyan/work/warehouse/bronze/order_events",
  "last-sequence-number" : 1,
  "last-updated-ms" : 1780502151043,
  "last-column-id" : 6,
  "current-schema-id" : 0,
  "schemas" : [ {
    "type" : "struct",
    "schema-id" : 0,
    "fields" : [ {
      "id" : 1,
      "name" : "raw_value",
      "required" : false,
      "type" : "string"
    }, {
      "id" : 2,
      "name" : "topic",
      "required" : false,
      "type" : "string"
    }, {
      "id" : 3,
      "name" : "partition",
      "required" : false,
      "type" : "int"
    }, {
      "id" : 4,
      "name" : "offset",
      "required" : false,
      "type" : "long"
    }, {
      "id" : 5,
      "name" : "kafka_timestamp",
      "required" : false,
      "type" : "timestamptz"
    }, {
      "id" : 6,
      "name" : "ingestion_time",
      "required" : false,
      "type" : "timestamptz"
    } ]
  } ],
  "default-spec-id" : 0,
  "partition-specs" : [ {
    "spec-id" : 0,
    "fields" : [ ]
  } ],
  "last-partition-id" : 999,
  "default-sort-order-id" : 0,
  "sort-orders" : [ {
    "order-id" : 0,
    "fields" : [ ]
  } ],
  "properties" : {
    "owner" : "jovyan",
    "write.parquet.compression-codec" : "zstd"
  },
  "current-snapshot-id" : 4546198925554470690,
  "refs" : {
    "main" : {
      "snapshot-id" : 4546198925554470690,
      "type" : "branch"
    }
  },
  "snapshots" : [ {
    "sequence-number" : 1,
    "snapshot-id" : 4546198925554470690,
    "timestamp-ms" : 1780502151043,
    "summary" : {
      "operation" : "append",
      "spark.app.id" : "local-1780502140441",
      "spark.sql.streaming.epochId" : "0",
      "spark.sql.streaming.queryId" : "0e40596a-1ded-41a8-91f4-5f2d1eeb2f52",
      "added-data-files" : "1",
      "added-records" : "1",
      "added-files-size" : "3178",
      "changed-partition-count" : "1",
      "total-records" : "1",
      "total-files-size" : "3178",
      "total-data-files" : "1",
      "total-delete-files" : "0",
      "total-position-deletes" : "0",
      "total-equality-deletes" : "0",
      "engine-version" : "3.5.0",
      "app-id" : "local-1780502140441",
      "engine-name" : "spark",
      "iceberg-version" : "Apache Iceberg 1.6.1 (commit 8e9d59d299be42b0bca9461457cd1e95dbaad086)"
    },
    "manifest-list" : "/home/jovyan/work/warehouse/bronze/order_events/metadata/snap-4546198925554470690-1-f65f7313-cf77-47ff-98cd-0cf688683aa1.avro",
    "schema-id" : 0
  } ],
  "statistics" : [ ],
  "partition-statistics" : [ ],
  "snapshot-log" : [ {
    "timestamp-ms" : 1780502151043,
    "snapshot-id" : 4546198925554470690
  } ],
  "metadata-log" : [ {
    "timestamp-ms" : 1780501270808,
    "metadata-file" : "/home/jovyan/work/warehouse/bronze/order_events/metadata/v1.metadata.json"
  } ]
}